extract_thinker/__init__.py
extract_thinker/batch_job.py
extract_thinker/completion_handler.py
extract_thinker/concatenation_handler.py
extract_thinker/document_loader/cached_document_loader.py
extract_thinker/document_loader/document_loader.py
extract_thinker/document_loader/document_loader_aws_textract.py
extract_thinker/document_loader/document_loader_azure_document_intelligence.py
extract_thinker/document_loader/document_loader_beautiful_soup.py
extract_thinker/document_loader/document_loader_data.py
extract_thinker/document_loader/document_loader_doc2txt.py
extract_thinker/document_loader/document_loader_docling.py
extract_thinker/document_loader/document_loader_easy_ocr.py
extract_thinker/document_loader/document_loader_google_document_ai.py
extract_thinker/document_loader/document_loader_llm_image.py
extract_thinker/document_loader/document_loader_markitdown.py
extract_thinker/document_loader/document_loader_mistral_ocr.py
extract_thinker/document_loader/document_loader_pdfplumber.py
extract_thinker/document_loader/document_loader_pypdf.py
extract_thinker/document_loader/document_loader_spreadsheet.py
extract_thinker/document_loader/document_loader_tesseract.py
extract_thinker/document_loader/document_loader_txt.py
extract_thinker/document_loader/llm_interceptor.py
extract_thinker/document_loader/loader_interceptor.py
extract_thinker/eval/DocumentHallucinationResults.py
extract_thinker/eval/HallucinationDetectionStrategy.py
extract_thinker/eval/HallucinationResult.py
extract_thinker/eval/__init__.py
extract_thinker/eval/cli.py
extract_thinker/eval/cost_metrics.py
extract_thinker/eval/dataset.py
extract_thinker/eval/evaluator.py
extract_thinker/eval/field_comparison.py
extract_thinker/eval/hallucination.py
extract_thinker/eval/metrics.py
extract_thinker/eval/report.py
extract_thinker/eval/setup.py
extract_thinker/exceptions.py
extract_thinker/extractor.py
extract_thinker/global_models.py
extract_thinker/image_splitter.py
extract_thinker/llm.py
extract_thinker-0.1.14.dist-info/LICENSE
extract_thinker-0.1.14.dist-info/METADATA
extract_thinker-0.1.14.dist-info/WHEEL
extract_thinker-0.1.14.dist-info/RECORD
