Metadata-Version: 2.3
Name: extract_thinker
Version: 0.1.14
Summary: Library to extract data from files and documents agnositicaly using LLMs
Author: Júlio Almeida
Author-email: enoch3712@gmail.com
Requires-Python: >=3.9,<3.14
Classifier: Programming Language :: Python :: 3
Classifier: Programming Language :: Python :: 3.9
Classifier: Programming Language :: Python :: 3.10
Classifier: Programming Language :: Python :: 3.11
Classifier: Programming Language :: Python :: 3.12
Classifier: Programming Language :: Python :: 3.13
Requires-Dist: cachetools (>=5.5.2)
Requires-Dist: instructor (>=1.8.3)
Requires-Dist: libmagic
Requires-Dist: litellm (>=1.71.1)
Requires-Dist: pillow (>=11.2.1,<12.0)
Requires-Dist: playwright (>=1.52.0)
Requires-Dist: pydantic (>=2.11.5)
Requires-Dist: pypdfium2 (>=4.30.1)
Requires-Dist: python-dotenv (>=1.1.0)
Requires-Dist: python-magic (>=0.4.27)
Requires-Dist: pyyaml (>=6.0.2)
Requires-Dist: tiktoken (>=0.8.0) ; python_version >= "3.9" and python_version < "3.13"
